LICENSE
README.md
pyproject.toml
setup.py
tactigon_ironboy/__init__.py
tactigon_ironboy/models.py
tactigon_ironboy.egg-info/PKG-INFO
tactigon_ironboy.egg-info/SOURCES.txt
tactigon_ironboy.egg-info/dependency_links.txt
tactigon_ironboy.egg-info/requires.txt
tactigon_ironboy.egg-info/top_level.txt