Metadata-Version: 2.4
Name: tactigon_ironboy
Version: 1.0.1
Summary: IronBoy Library
Home-page: https://nextind.eu
Author: Next Industries s.r.l.
Author-email: info@nextind.eu
License: MIT
Keywords: tactigon,arduino,robot,cobot,ironboy
Classifier: Programming Language :: Python :: 3
Classifier: License :: OSI Approved :: MIT License
Classifier: Operating System :: OS Independent
Requires-Python: >=3.8.0
License-File: LICENSE
Requires-Dist: bleak==2.0.0
Dynamic: author
Dynamic: author-email
Dynamic: classifier
Dynamic: description
Dynamic: description-content-type
Dynamic: home-page
Dynamic: keywords
Dynamic: license
Dynamic: license-file
Dynamic: requires-dist
Dynamic: requires-python
Dynamic: summary
